GNUmakefile
LICENSE
MANIFEST.in
NOTICE
makefile
setup.py
dtflickr/__init__.py
dtflickr/_methods.py
dtflickr/update.py
dtflickr.egg-info/PKG-INFO
dtflickr.egg-info/SOURCES.txt
dtflickr.egg-info/dependency_links.txt
dtflickr.egg-info/requires.txt
dtflickr.egg-info/top_level.txt