Metadata-Version: 1.0
Name: dtflickr
Version: 1.5
Summary: Spiffy Flickr API library using JSON
Home-page: http://code.douglasthrift.net/trac/dtflickr
Author: Douglas Thrift
Author-email: douglas@douglasthrift.net
License: Apache License, Version 2.0
Keywords: flickr api
Platform: any
Classifier: Development Status :: 5 - Production/Stable
Classifier: Intended Audience :: Developers
Classifier: License :: OSI Approved :: Apache Software License
Classifier: Operating System :: OS Independent
Classifier: Programming Language :: Python
Classifier: Topic :: Multimedia :: Graphics
Classifier: Topic :: Software Development :: Libraries :: Python Modules
